{
  "profile": {
    "name": "Yisu Kim"
  },
  "blog": {
    "author": "Yisu Kim",
    "description": "A software engineer's call-by-need articles on JavaScript, TypeScript, React and more."
  },
  "page": {
    "posts": "Posts"
  },
  "notFound": {
    "title": "The page cannot be found.",
    "description": "Please check if the URL you entered is correct.",
    "redirectText": "View all posts"
  },
  "language": {
    "toggle": "Toggle Korean/English"
  },
  "contact": {
    "email": "Send an email",
    "github": "Visit GitHub profile",
    "linkedin": "Visit LinkedIn profile"
  }
}
